fate_client/__init__.py
fate_client/settings.yaml
fate_client/flow_cli/__init__.py
fate_client/flow_cli/flow.py
fate_client/flow_cli/commands/__init__.py
fate_client/flow_cli/commands/client.py
fate_client/flow_cli/commands/data.py
fate_client/flow_cli/commands/job.py
fate_client/flow_cli/commands/log.py
fate_client/flow_cli/commands/model.py
fate_client/flow_cli/commands/output.py
fate_client/flow_cli/commands/permission.py
fate_client/flow_cli/commands/provider.py
fate_client/flow_cli/commands/server.py
fate_client/flow_cli/commands/site.py
fate_client/flow_cli/commands/table.py
fate_client/flow_cli/commands/task.py
fate_client/flow_cli/commands/test.py
fate_client/flow_cli/utils/__init__.py
fate_client/flow_cli/utils/args_desc.py
fate_client/flow_cli/utils/cli_args.py
fate_client/flow_cli/utils/cli_utils.py
fate_client/flow_sdk/__init__.py
fate_client/flow_sdk/_client.py
fate_client/flow_sdk/api/__init__.py
fate_client/flow_sdk/api/client.py
fate_client/flow_sdk/api/data.py
fate_client/flow_sdk/api/job.py
fate_client/flow_sdk/api/log.py
fate_client/flow_sdk/api/model.py
fate_client/flow_sdk/api/output.py
fate_client/flow_sdk/api/permission.py
fate_client/flow_sdk/api/provider.py
fate_client/flow_sdk/api/service.py
fate_client/flow_sdk/api/site.py
fate_client/flow_sdk/api/table.py
fate_client/flow_sdk/api/task.py
fate_client/flow_sdk/api/test.py
fate_client/flow_sdk/utils/__init__.py
fate_client/flow_sdk/utils/base_utils.py
fate_client/flow_sdk/utils/io_utils.py
fate_client/flow_sdk/utils/params_utils.py
fate_client/pipeline/__init__.py
fate_client/pipeline/pipeline.py
fate_client/pipeline/pipeline_cli.py
fate_client/pipeline/component_define/__init__.py
fate_client/pipeline/component_define/fate/__init__.py
fate_client/pipeline/component_define/fate/coordinated_linr.yaml
fate_client/pipeline/component_define/fate/coordinated_lr.yaml
fate_client/pipeline/component_define/fate/data_split.yaml
fate_client/pipeline/component_define/fate/dataframe_io_test.yaml
test_fate_client-2.0.1b0.dist-info/METADATA
test_fate_client-2.0.1b0.dist-info/WHEEL
test_fate_client-2.0.1b0.dist-info/entry_points.txt
test_fate_client-2.0.1b0.dist-info/top_level.txt
test_fate_client-2.0.1b0.dist-info/RECORD
