Metadata-Version: 2.1
Name: test-fate-client
Version: 2.0.1b0
Summary: Clients for FATE, supply pipeline this version
Home-page: https://fate.fedai.org/
Author: FederatedAI
Author-email: contact@FedAI.org
Requires-Python: >=3.8
Requires-Dist: click
Requires-Dist: pandas
Requires-Dist: psutil
Requires-Dist: requests
Requires-Dist: requests-toolbelt
Requires-Dist: ruamel.yaml
Requires-Dist: setuptools
Requires-Dist: networkx
Requires-Dist: pydantic
Provides-Extra: fate
Requires-Dist: testfate (==2.0.0b0) ; extra == 'fate'
Provides-Extra: fate_flow
Requires-Dist: testabc (==1.14.0) ; extra == 'fate_flow'
